c7n_huaweicloud/__init__.py
c7n_huaweicloud/actions/__init__.py
c7n_huaweicloud/actions/autotag.py
c7n_huaweicloud/actions/base.py
c7n_huaweicloud/actions/elb.py
c7n_huaweicloud/actions/tms.py
c7n_huaweicloud/client.py
c7n_huaweicloud/cts.py
c7n_huaweicloud/entry.py
c7n_huaweicloud/filters/__init__.py
c7n_huaweicloud/filters/ces.py
c7n_huaweicloud/filters/config.py
c7n_huaweicloud/filters/elb.py
c7n_huaweicloud/filters/revisions.py
c7n_huaweicloud/filters/tms.py
c7n_huaweicloud/filters/transfer.py
c7n_huaweicloud/handler.py
c7n_huaweicloud/marker_pagination.py
c7n_huaweicloud/mu.py
c7n_huaweicloud/output.py
c7n_huaweicloud/policy.py
c7n_huaweicloud/provider.py
c7n_huaweicloud/query.py
c7n_huaweicloud/resources/__init__.py
c7n_huaweicloud/resources/antiddos.py
c7n_huaweicloud/resources/cbr_backup.py
c7n_huaweicloud/resources/cbr_vault.py
c7n_huaweicloud/resources/ces.py
c7n_huaweicloud/resources/coc.py
c7n_huaweicloud/resources/config.py
c7n_huaweicloud/resources/cts-notification-func.py
c7n_huaweicloud/resources/cts-notification-smn.py
c7n_huaweicloud/resources/cts-tracker.py
c7n_huaweicloud/resources/deh.py
c7n_huaweicloud/resources/ecs.py
c7n_huaweicloud/resources/elb.py
c7n_huaweicloud/resources/er.py
c7n_huaweicloud/resources/evs.py
c7n_huaweicloud/resources/functiongraph.py
c7n_huaweicloud/resources/iam.py
c7n_huaweicloud/resources/ims.py
c7n_huaweicloud/resources/kms.py
c7n_huaweicloud/resources/lts-transfer.py
c7n_huaweicloud/resources/nat.py
c7n_huaweicloud/resources/obs.py
c7n_huaweicloud/resources/organizations.py
c7n_huaweicloud/resources/ram.py
c7n_huaweicloud/resources/resource_map.py
c7n_huaweicloud/resources/secmaster.py
c7n_huaweicloud/resources/sfsturbo.py
c7n_huaweicloud/resources/smn.py
c7n_huaweicloud/resources/transfer.py
c7n_huaweicloud/resources/vpc.py
c7n_huaweicloud-0.1.1.dist-info/METADATA
c7n_huaweicloud-0.1.1.dist-info/WHEEL
c7n_huaweicloud-0.1.1.dist-info/RECORD
