Metadata-Version: 2.1
Name: c7n_huaweicloud
Version: 0.1.1
Summary: Cloud Custodian - Huawei Cloud Support
Home-page: https://cloudcustodian.io
License: Apache-2.0
Author: Cloud Custodian Project
Requires-Python: >=3.8,<4.0
Classifier: License :: OSI Approved :: Apache Software License
Classifier: Programming Language :: Python :: 3
Classifier: Programming Language :: Python :: 3.8
Classifier: Programming Language :: Python :: 3.9
Classifier: Programming Language :: Python :: 3.10
Classifier: Programming Language :: Python :: 3.11
Classifier: Programming Language :: Python :: 3.12
Classifier: Topic :: System :: Distributed Computing
Classifier: Topic :: System :: Systems Administration
Requires-Dist: esdk-obs-python (>=3.24.12,<4.0.0)
Requires-Dist: huaweicloudsdkantiddos (>=3.1.138,<4.0.0)
Requires-Dist: huaweicloudsdkcbr (>=3.1.138,<4.0.0)
Requires-Dist: huaweicloudsdkces (>=3.1.138,<4.0.0)
Requires-Dist: huaweicloudsdkcoc (>=3.1.138,<4.0.0)
Requires-Dist: huaweicloudsdkconfig (>=3.1.138,<4.0.0)
Requires-Dist: huaweicloudsdkcts (>=3.1.139,<4.0.0)
Requires-Dist: huaweicloudsdkdeh (>=3.1.138,<4.0.0)
Requires-Dist: huaweicloudsdkecs (>=3.1.138,<4.0.0)
Requires-Dist: huaweicloudsdkeg (>=3.1.138,<4.0.0)
Requires-Dist: huaweicloudsdkeip (>=3.1.138,<4.0.0)
Requires-Dist: huaweicloudsdkelb (>=3.1.138,<4.0.0)
Requires-Dist: huaweicloudsdker (>=3.1.138,<4.0.0)
Requires-Dist: huaweicloudsdkevs (>=3.1.138,<4.0.0)
Requires-Dist: huaweicloudsdkfunctiongraph (>=3.1.141,<4.0.0)
Requires-Dist: huaweicloudsdkgeip (>=3.1.138,<4.0.0)
Requires-Dist: huaweicloudsdkiam (>=3.1.140,<4.0.0)
Requires-Dist: huaweicloudsdkims (>=3.1.138,<4.0.0)
Requires-Dist: huaweicloudsdkkms (>=3.1.138,<4.0.0)
Requires-Dist: huaweicloudsdklts (>=3.1.138,<4.0.0)
Requires-Dist: huaweicloudsdknat (>=3.1.138,<4.0.0)
Requires-Dist: huaweicloudsdkobs (>=3.1.138,<4.0.0)
Requires-Dist: huaweicloudsdkorganizations (>=3.1.138,<4.0.0)
Requires-Dist: huaweicloudsdkram (>=3.1.138,<4.0.0)
Requires-Dist: huaweicloudsdksecmaster (>=3.1.140,<4.0.0)
Requires-Dist: huaweicloudsdksfsturbo (>=3.1.138,<4.0.0)
Requires-Dist: huaweicloudsdksmn (>=3.1.138,<4.0.0)
Requires-Dist: huaweicloudsdktms (>=3.1.138,<4.0.0)
Requires-Dist: huaweicloudsdkvpc (>=3.1.138,<4.0.0)
Requires-Dist: jsonpatch (>=1.25,<2.0)
Requires-Dist: python-dateutil (>=2.8.2,<3.0.0)
Project-URL: Documentation, https://cloudcustodian.io/docs/
Project-URL: Repository, https://github.com/cloud-custodian/cloud-custodian
